LICENSE
Morton3D.py
README.md
setup.cfg
setup.py
Morton3D/Morton3D.py
Morton3D/__init__.py
Morton3D.egg-info/PKG-INFO
Morton3D.egg-info/SOURCES.txt
Morton3D.egg-info/dependency_links.txt
Morton3D.egg-info/top_level.txt