Metadata-Version: 2.1
Name: Morton3D
Version: 1.0.1
Summary: Efficient 3D Morton Encoding and Decoding
Home-page: https://github.com/Jianningli/Morton3D
Author: Jianning Li
Author-email: jianningli.me@gmail.com
Maintainer: Jianning Li
Maintainer-email: jianningli.me@gmail.com
License: MIT
Download-URL: https://github.com/Jianningli/Morton3D/archive/1.0.1.zip
Keywords: z-order,morton order,3D hashing
Platform: UNKNOWN
Classifier: Development Status :: 3 - Alpha
Classifier: Intended Audience :: Developers
Classifier: Topic :: Software Development :: Build Tools
Classifier: License :: OSI Approved :: MIT License
Classifier: Programming Language :: Python :: 3
